LICENSE
MANIFEST.in
README.rst
setup.py
django_bcrypt/__init__.py
django_bcrypt/models.py
django_bcrypt/tests.py
django_bcrypt.egg-info/PKG-INFO
django_bcrypt.egg-info/SOURCES.txt
django_bcrypt.egg-info/dependency_links.txt
django_bcrypt.egg-info/requires.txt
django_bcrypt.egg-info/top_level.txt