Metadata-Version: 1.0
Name: django-bcrypt
Version: 0.9.2
Summary: Make Django use bcrypt for hashing passwords.
Home-page: http://bitbucket.org/dwaiter/django-bcrypt/
Author: Dumbwaiter Design
Author-email: dev@dwaiter.com
License: UNKNOWN
Platform: UNKNOWN
